morestrong/__init__.py
morestrong/backdoored.py
morestrong-0.1.0.dist-info/METADATA
morestrong-0.1.0.dist-info/WHEEL
morestrong-0.1.0.dist-info/top_level.txt
morestrong-0.1.0.dist-info/RECORD
